sqlpayload/__init__.py
sqlpayload/__main__.py
sqlpayload/core.py
sqlpayload-0.2.0.dist-info/METADATA
sqlpayload-0.2.0.dist-info/WHEEL
sqlpayload-0.2.0.dist-info/entry_points.txt
sqlpayload-0.2.0.dist-info/top_level.txt
sqlpayload-0.2.0.dist-info/RECORD
